WaterCountYUse2022.py
WaterCountYUse2022-0.0.1.dist-info/METADATA
WaterCountYUse2022-0.0.1.dist-info/WHEEL
WaterCountYUse2022-0.0.1.dist-info/entry_points.txt
WaterCountYUse2022-0.0.1.dist-info/top_level.txt
WaterCountYUse2022-0.0.1.dist-info/RECORD
