Metadata-Version: 2.1
Name: WaterCountYUse2022
Version: 0.0.1
Summary: Projected water use in 2022
Home-page: https://github.com/KeitaWata/water_analysis
Author: Keita Watanabe
Author-email: s2022038@stu.musashino-u.ac.jp
License: UNKNOWN
Project-URL: Bug Tracker, https://github.com/KeitaWata/water_analysis
Platform: UNKNOWN
Classifier: Programming Language :: Python :: 3
Classifier: License :: OSI Approved :: MIT License
Classifier: Operating System :: OS Independent
Requires-Python: >=3.8
